lbibhelper/__init__.py
lbibhelper/cli.py
lbibhelper/lbibhelper.py
lbibhelper/core/__init__.py
lbibhelper/core/plot.py
lbibhelper/core/settings.py
lbibhelper/core/util.py
lbibhelper/fit/__init__.py
lbibhelper/fit/solver.py
lbibhelper/report_processor/__init__.py
lbibhelper/report_processor/solver_processor.py
lbibhelper/report_processor/video.py
lbibhelper/report_processor/vtk_cell_processor.py
lbibhelper-0.1.1.dist-info/AUTHORS.rst
lbibhelper-0.1.1.dist-info/LICENSE
lbibhelper-0.1.1.dist-info/METADATA
lbibhelper-0.1.1.dist-info/WHEEL
lbibhelper-0.1.1.dist-info/entry_points.txt
lbibhelper-0.1.1.dist-info/top_level.txt
lbibhelper-0.1.1.dist-info/RECORD
