Metadata-Version: 2.1
Name: lbibhelper
Version: 0.1.1
Summary: Python helper for easy manage LBIBCell simulation
Home-page: https://github.com/wyq977/lbibhelper
Author: Yongqi Wang
Author-email: wangyq977@gmail.com
License: MIT license
Keywords: lbibhelper
Platform: UNKNOWN
Classifier: Development Status :: 2 - Pre-Alpha
Classifier: Intended Audience :: Developers
Classifier: License :: OSI Approved :: MIT License
Classifier: Natural Language :: English
Classifier: Programming Language :: Python :: 3
Classifier: Programming Language :: Python :: 3.6
Classifier: Programming Language :: Python :: 3.7
Classifier: Programming Language :: Python :: 3.8
Requires-Python: >=3.6
